Metadata-Version: 2.1
Name: logcolor
Version: 1.1.0
Summary: Colored logs
Home-page: http://sendapatch.se/
Author: Ludvig Ericson
Author-email: ludvig@lericson.se
